Perceptron/Perceptron.py
Perceptron/__init__.py
OneNeuron-0.0.2.dist-info/LICENSE
OneNeuron-0.0.2.dist-info/METADATA
OneNeuron-0.0.2.dist-info/WHEEL
OneNeuron-0.0.2.dist-info/top_level.txt
OneNeuron-0.0.2.dist-info/RECORD
