Metadata-Version: 2.1
Name: OneNeuron
Version: 0.0.2
Summary: OneNeuron Package
Home-page: https://github.com/pradhami/Perceptron
Author: Amit Kumar Pradhan
Author-email: amitpradhands@gmail.com
License: UNKNOWN
Project-URL: Bug Tracker, https://github.com/pradhami/Perceptron/issues
Platform: UNKNOWN
Classifier: Programming Language :: Python :: 3
Classifier: License :: OSI Approved :: MIT License
Classifier: Operating System :: OS Independent
Requires-Python: >=3.6
License-File: LICENSE
Requires-Dist: numpy
